tensortract2/__init__.py
tensortract2/tensortract2.py
tensortract2/cfg/tensortract2_version_uc81_am100.yaml
tensortract2/modules/__init__.py
tensortract2/modules/audioprocessing_functional.py
tensortract2/modules/conformer.py
tensortract2/modules/motor_encoder.py
tensortract2/modules/utils.py
tensortract2/modules/vtl.py
tensortract2/modules/wavlm.py
tensortract2/modules/hifigan/__init__.py
tensortract2/modules/hifigan/condition.py
tensortract2/modules/hifigan/conditional_layer.py
tensortract2/modules/hifigan/generator.py
tensortract2/modules/hifigan/resblock.py
tensortract2/modules/titanet/__init__.py
tensortract2/modules/titanet/nemo_audioprocessing.py
tensortract2/modules/titanet/nemo_decoder.py
tensortract2/modules/titanet/nemo_encoder.py
tensortract2/modules/titanet/nemo_jasper.py
tensortract2/modules/titanet/nemo_tdnn.py
tensortract2/modules/titanet/titanet.py
tensortract2-0.0.4.dist-info/licenses/LICENSE
tensortract2-0.0.4.dist-info/METADATA
tensortract2-0.0.4.dist-info/WHEEL
tensortract2-0.0.4.dist-info/top_level.txt
tensortract2-0.0.4.dist-info/RECORD
