Metadata-Version: 2.4
Name: tensortract2
Version: 0.0.4
Summary: A PyTorch implementation of TensorTract2
Home-page: https://github.com/Altavo/tensortract2
Author: Paul Krug
License: Commons Clause License Condition v1.0
License-File: LICENSE
Requires-Dist: einops>=0.8.1
Requires-Dist: numpy
Requires-Dist: pytorch-tcn==1.2.3
Requires-Dist: requests>=2.32.3
Requires-Dist: target-approximation>=0.0.5
Requires-Dist: torch>=2.6.0
Requires-Dist: torchaudio>=2.6.0
Requires-Dist: transformers>=4.50.3
Requires-Dist: tqdm
Requires-Dist: soundfile>=0.13.1
Dynamic: author
Dynamic: description
Dynamic: description-content-type
Dynamic: home-page
Dynamic: license
Dynamic: license-file
Dynamic: requires-dist
Dynamic: summary
